{
	"class" : {
		 },
	"instance" : {
		"allFiltersOff" : "EiichiroIto 12/23/2017 18:59:53",
		"applyFiltersTo:" : "EiichiroIto 12/23/2017 18:59:53",
		"applyMosaicFilter" : "EiichiroIto 12/23/2017 18:59:53",
		"applyPixelateFilter" : "EiichiroIto 12/23/2017 18:59:53",
		"applyPointillizeFilter" : "EiichiroIto 12/23/2017 18:59:53",
		"applyStaticFiltersTo:" : "EiichiroIto 12/23/2017 18:59:53",
		"applyWaterRippleFilter" : "EiichiroIto 12/23/2017 18:59:53",
		"blur" : "EiichiroIto 12/23/2017 18:59:53",
		"blur:" : "EiichiroIto 12/23/2017 18:59:53",
		"brightnessShift" : "EiichiroIto 12/23/2017 18:59:53",
		"brightnessShift:" : "EiichiroIto 12/23/2017 18:59:53",
		"clearFilterCaches" : "EiichiroIto 12/23/2017 18:59:53",
		"filtersActive" : "EiichiroIto 12/23/2017 18:59:53",
		"fisheye" : "EiichiroIto 12/23/2017 18:59:53",
		"fisheye:" : "EiichiroIto 12/23/2017 18:59:53",
		"hueShift" : "EiichiroIto 12/23/2017 18:59:53",
		"hueShift:" : "EiichiroIto 12/23/2017 18:59:53",
		"initialize" : "EiichiroIto 12/23/2017 18:59:53",
		"mosaicCount" : "EiichiroIto 12/23/2017 18:59:53",
		"mosaicCount:" : "EiichiroIto 12/23/2017 18:59:53",
		"pixelateCount" : "EiichiroIto 12/23/2017 18:59:53",
		"pixelateCount:" : "EiichiroIto 12/23/2017 18:59:53",
		"pointillizeSize" : "EiichiroIto 12/23/2017 18:59:53",
		"pointillizeSize:" : "EiichiroIto 12/23/2017 18:59:53",
		"rand" : "EiichiroIto 12/23/2017 18:59:53",
		"resetAllFilters" : "EiichiroIto 12/23/2017 18:59:53",
		"resultForm" : "EiichiroIto 12/23/2017 18:59:53",
		"saturationShift" : "EiichiroIto 12/23/2017 18:59:53",
		"saturationShift:" : "EiichiroIto 12/23/2017 18:59:53",
		"waterRippleRate" : "EiichiroIto 12/23/2017 18:59:53",
		"waterRippleRate:" : "EiichiroIto 12/23/2017 18:59:53",
		"whirl" : "EiichiroIto 12/23/2017 18:59:53",
		"whirl:" : "EiichiroIto 12/23/2017 18:59:53" } }
